{
  "include": [
    "backend",
    "tests"
  ],
  "exclude": [
    "**/__pycache__",
    "**/.pytest_cache",
    "**/node_modules",
    "**/.venv",
    "**/venv"
  ],
  "ignore": [
    "scripts"
  ],
  "defineConstant": {
    "DEBUG": true
  },
  "stubPath": "typings",
  "reportMissingImports": "warning",
  "reportMissingTypeStubs": "warning",
  "pythonVersion": "3.9",
  "pythonPlatform": "Darwin",
  "executionEnvironments": [
    {
      "root": ".",
      "pythonVersion": "3.9",
      "pythonPlatform": "Darwin",
      "extraPaths": [
        "${workspaceFolder}",
        "${workspaceFolder}/backend"
      ]
    }
  ],
  "typeCheckingMode": "standard",
  "reportAttributeAccessIssue": "error",
  "reportIndexIssue": "error",
  "reportOperatorIssue": "error",
  "reportArgumentType": "error",
  "reportAssignmentType": "error",
  "reportOptionalMemberAccess": "error",
  "reportOptionalSubscript": "error",
  "reportGeneralTypeIssues": "error",
  "reportUnusedImport": "error",
  "reportUnusedClass": "warning",
  "reportUnusedFunction": false,
  "reportUnusedVariable": "warning",
  "reportDuplicateImport": "error",
  "reportWildcardImportFromLibrary": "error",
  "reportPrivateUsage": "warning",
  "reportConstantRedefinition": "error",
  "reportIncompatibleMethodOverride": "error",
  "reportIncompatibleVariableOverride": "error",
  "reportUntypedFunctionDecorator": "warning",
  "reportUntypedClassDecorator": "warning",
  "reportUntypedBaseClass": "warning",
  "reportUntypedNamedTuple": "warning",
  "reportCallInDefaultInitializer": false,
  "reportImplicitStringConcatenation": "warning",
  "reportMissingSuperCall": false,
  "reportPropertyTypeMismatch": "error",
  "reportUninitializedInstanceVariable": "warning",
  "reportUnnecessaryTypeIgnoreComment": "warning",
  "reportMatchNotExhaustive": "warning"
}
